quanchecker/__init__.py
quanchecker/checker_lib.py
quanchecker-0.0.7.dist-info/METADATA
quanchecker-0.0.7.dist-info/WHEEL
quanchecker-0.0.7.dist-info/top_level.txt
quanchecker-0.0.7.dist-info/RECORD
