Metadata-Version: 2.1
Name: quanchecker
Version: 0.0.7
Summary: Checker Library for QuanC
Author: QuanC
Author-email: <project.quanc@gmail.com>
Keywords: python,quanc
Classifier: Development Status :: 1 - Planning
Classifier: Intended Audience :: Developers
Classifier: Programming Language :: Python :: 3
Classifier: Operating System :: Unix
Classifier: Operating System :: MacOS :: MacOS X
Classifier: Operating System :: Microsoft :: Windows
Requires-Dist: requests
Requires-Dist: docker
